jsonbourne/__about__.py
jsonbourne/__init__.py
jsonbourne/__main__.py
jsonbourne/core.py
jsonbourne/dev/__init__.py
jsonbourne/fastapi.py
jsonbourne/helpers.py
jsonbourne/httpx.py
jsonbourne/json_arr.py
jsonbourne/jsonlib.py
jsonbourne/protocols.py
jsonbourne/py.typed
jsonbourne/pydantic.py
jsonbourne/trydantic.py
jsonbourne/types.py
jsonbourne-0.32.1.dist-info/WHEEL
jsonbourne-0.32.1.dist-info/METADATA
jsonbourne-0.32.1.dist-info/RECORD
