Metadata-Version: 2.3
Name: jsonbourne
Version: 0.32.1
Summary: EZPZ JSON
Keywords: dgpy,json,orjson,pydantic,rapidjson
Author: jesse
Author-email: jesse <jesse@dgi.com>
Classifier: Development Status :: 5 - Production/Stable
Classifier: Intended Audience :: Developers
Classifier: License :: OSI Approved :: MIT License
Classifier: Programming Language :: Python
Classifier: Programming Language :: Python :: 3 :: Only
Classifier: Programming Language :: Python :: 3.11
Classifier: Programming Language :: Python :: 3.12
Classifier: Programming Language :: Python :: 3.13
Classifier: Programming Language :: Python :: 3.14
Classifier: Typing :: Typed
Requires-Dist: httpx>=0.27 ; extra == 'httpx'
Requires-Dist: orjson>=3.10.7 ; extra == 'orjson'
Requires-Dist: pydantic>=2.8.2 ; extra == 'pydantic'
Requires-Dist: pytest>=8.3.2 ; extra == 'test'
Requires-Python: >=3.11, <4.0
Project-URL: Homepage, https://github.com/dynamic-graphics-inc/dgpy-libs/tree/main/libs/jsonbourne
Project-URL: Repository, https://github.com/dynamic-graphics-inc/dgpy-libs
Provides-Extra: httpx
Provides-Extra: orjson
Provides-Extra: pydantic
Provides-Extra: test
